jerrycan/Config.py
jerrycan/__init__.py
jerrycan/base.py
jerrycan/enums.py
jerrycan/exceptions.py
jerrycan/initialize.py
jerrycan/wsgi.py
jerrycan/background/__init__.py
jerrycan/background/telegram.py
jerrycan/db/ApiKey.py
jerrycan/db/IDModelMixin.py
jerrycan/db/ModelMixin.py
jerrycan/db/TelegramChatId.py
jerrycan/db/User.py
jerrycan/db/__init__.py
jerrycan/routes/__init__.py
jerrycan/routes/decorators.py
jerrycan/routes/static.py
jerrycan/routes/user_management.py
jerrycan/routes/api/__init__.py
jerrycan/routes/api/user_management.py
jerrycan/test/TestFramework.py
jerrycan/test/__init__.py
jerrycan/test/mocks.py
jerrycan/test/db/TestApiKey.py
jerrycan/test/db/TestIDModelMixin.py
jerrycan/test/db/TestTelegramChatId.py
jerrycan/test/db/TestUser.py
jerrycan/test/db/__init__.py
jerrycan/test/misc/TestApiCalls.py
jerrycan/test/misc/TestConfig.py
jerrycan/test/misc/TestErrorHandling.py
jerrycan/test/misc/TestInitialization.py
jerrycan/test/misc/TestTelegramBackground.py
jerrycan/test/misc/TestWsgi.py
jerrycan/test/misc/__init__.py
jerrycan/test/routes/TestForgotRoute.py
jerrycan/test/routes/TestLoginRoute.py
jerrycan/test/routes/TestProfileRoute.py
jerrycan/test/routes/TestRegisterRoute.py
jerrycan/test/routes/TestRegisterTelegramRoute.py
jerrycan/test/routes/TestStaticRoutes.py
jerrycan/test/routes/__init__.py
jerrycan/test/routes/api/TestApiKeyRoute.py
jerrycan/test/routes/api/__init__.py
jerrycan-0.3.4.dist-info/LICENSE
jerrycan-0.3.4.dist-info/METADATA
jerrycan-0.3.4.dist-info/WHEEL
jerrycan-0.3.4.dist-info/top_level.txt
jerrycan-0.3.4.dist-info/RECORD
