Metadata-Version: 2.1
Name: jerrycan
Version: 0.3.4
Summary: A python library that contains commonly used routes, database models and functions for flask applications
Home-page: https://gitlab.namibsun.net/namibsun/python/jerrycan
Author: Hermann Krumrey
Author-email: hermann@krumreyh.com
License: GNU GPL3
Platform: UNKNOWN
Classifier: License :: OSI Approved :: GNU General Public License v3 (GPLv3)
License-File: LICENSE
Requires-Dist: flask
Requires-Dist: flask-sqlalchemy
Requires-Dist: flask-login
Requires-Dist: sqlalchemy
Requires-Dist: cheroot
Requires-Dist: werkzeug
Requires-Dist: sentry-sdk[flask]
Requires-Dist: blinker
Requires-Dist: bokkichat
Requires-Dist: python-telegram-bot
Requires-Dist: puffotter[crypto]
